imzy/__init__.py
imzy/_hdf5_mixin.py
imzy/_typing.py
imzy/hookspec.py
imzy/plugins.py
imzy/processing.py
imzy/utilities.py
imzy/_centroids/__init__.py
imzy/_centroids/_base.py
imzy/_centroids/_extract.py
imzy/_centroids/_hdf5_store.py
imzy/_centroids/_memory_store.py
imzy/_centroids/_zarr_store.py
imzy/_normalizations/__init__.py
imzy/_normalizations/_extract.py
imzy/_normalizations/_hdf5_store.py
imzy/_readers/__init__.py
imzy/_readers/_base.py
imzy/_readers/bruker/THIRD-PARTY-LICENSE-README.txt
imzy/_readers/bruker/__init__.py
imzy/_readers/bruker/_mixin.py
imzy/_readers/bruker/_neoflex.py
imzy/_readers/bruker/_tdf.py
imzy/_readers/bruker/_tsf.py
imzy/_readers/bruker/libtimsdata.so
imzy/_readers/bruker/timsdata.dll
imzy/_readers/bruker/utilities.py
imzy/_readers/imzml/__init__.py
imzy/_readers/imzml/_ims.py
imzy/_readers/imzml/_imzml.py
imzy/_readers/imzml/_ms.py
imzy/_readers/imzml/_ontology.py
imzy/_readers/imzml/_uo.py
imzy/_readers/waters/MassLynxLockMassProcessor.py
imzy/_readers/waters/MassLynxRaw.dll
imzy/_readers/waters/MassLynxRaw.lib
imzy/_readers/waters/MassLynxRawChromatogramReader.py
imzy/_readers/waters/MassLynxRawInfoReader.py
imzy/_readers/waters/MassLynxRawReader.py
imzy/_readers/waters/MassLynxRawScanReader.py
imzy/_readers/waters/__init__.py
imzy/_readers/waters/_raw.py
imzy/_readers/waters/cdt.dll
imzy-0.2.9.dist-info/METADATA
imzy-0.2.9.dist-info/WHEEL
imzy-0.2.9.dist-info/licenses/LICENSE
imzy-0.2.9.dist-info/RECORD
