Metadata-Version: 2.4
Name: imzy
Version: 0.2.9
Summary: imzy: A new reader interface to imzML and other imaging mass spectrometry formats.
Project-URL: homepage, https://github.com/vandeplaslab/imzy
Project-URL: repository, https://github.com/vandeplaslab/imzy
Author-email: "Lukasz G. Migas" <lukas.migas@yahoo.com>
License: BSD 3-Clause License
License-File: LICENSE
Classifier: Development Status :: 3 - Alpha
Classifier: Intended Audience :: Education
Classifier: Intended Audience :: Science/Research
Classifier: License :: OSI Approved :: MIT License
Classifier: Natural Language :: English
Classifier: Operating System :: MacOS
Classifier: Operating System :: Microsoft :: Windows
Classifier: Operating System :: POSIX
Classifier: Operating System :: Unix
Classifier: Programming Language :: Python
Classifier: Programming Language :: Python :: 3
Classifier: Programming Language :: Python :: 3 :: Only
Classifier: Programming Language :: Python :: 3.9
Classifier: Programming Language :: Python :: 3.10
Classifier: Programming Language :: Python :: 3.11
Classifier: Programming Language :: Python :: 3.12
Classifier: Topic :: Scientific/Engineering :: Bio-Informatics
Classifier: Topic :: Scientific/Engineering :: Visualization
Classifier: Topic :: Utilities
Classifier: Typing :: Typed
Requires-Python: >=3.9
Requires-Dist: ims-utils>=0.1.8
Requires-Dist: koyo
Requires-Dist: natsort
Requires-Dist: numba
Requires-Dist: numpy
Requires-Dist: pluggy
Requires-Dist: scipy
Requires-Dist: tqdm
Requires-Dist: yoki5
Provides-Extra: all
Requires-Dist: dask; extra == 'all'
Requires-Dist: h5py; extra == 'all'
Requires-Dist: hdf5plugin; extra == 'all'
Requires-Dist: matplotlib; extra == 'all'
Requires-Dist: rechunker; extra == 'all'
Requires-Dist: yoki5; extra == 'all'
Requires-Dist: zarr; extra == 'all'
Provides-Extra: hdf5
Requires-Dist: h5py; extra == 'hdf5'
Requires-Dist: hdf5plugin; extra == 'hdf5'
Requires-Dist: yoki5; extra == 'hdf5'
Provides-Extra: plot
Requires-Dist: matplotlib; extra == 'plot'
Provides-Extra: test
Requires-Dist: dask; extra == 'test'
Requires-Dist: h5py; extra == 'test'
Requires-Dist: hdf5plugin; extra == 'test'
Requires-Dist: matplotlib; extra == 'test'
Requires-Dist: pytest-cov>=6.1.1; extra == 'test'
Requires-Dist: pytest>=8.3.5; extra == 'test'
Requires-Dist: rechunker; extra == 'test'
Requires-Dist: yoki5; extra == 'test'
Requires-Dist: zarr; extra == 'test'
Provides-Extra: zarr
Requires-Dist: dask; extra == 'zarr'
Requires-Dist: rechunker; extra == 'zarr'
Requires-Dist: zarr; extra == 'zarr'
